[
  {
    "name": " Dsa Sorting Visualizer",
    "content": "An interactive React tool to visualize and understand sorting algorithms.",
    "stack": "React-J ,Node-js ",
    "files": "https://github.com/esh-dev257/DSA-Algos-Sorting-Visualizer",
    "link": "https://dsa-algo-sorting-visualizer.netlify.app/",
    "imgs": "https://i.imgur.com/2voYcWE.png"
  },
  {
    "name": "Text to Speech ",
    "content": "A React app that converts text into speech using the Web Speech API. Users can input text, select voices, and adjust pitch, speed, and volume.",
    "stack": "React-J ,Node-js , Web Speech API",
    "files": "https://github.com/esh-dev257/Text-to-Speech-Converter",
    "link": "https://test-to-speech-converter-react.netlify.app/",
    "imgs": "https://i.imgur.com/OAtBqzo.png"
  },
  {
    "name": "Typing-Speed ",
    "content": "A React app to test typing speed and accuracy.",
    "stack": "React-J ,Node-js , Tailwind, Firebase ",
    "files": "https://github.com/esh-dev257/Typing-speed-checker",
    "link": "https://typingspeed-checker.netlify.app/",
    "imgs": "https://i.imgur.com/fO3hRwh.png"
  },
  {
    "name": "Google Clone",
    "content": "Its a Clone of Google Keep made using React-js",
    "stack": "React-Js,Node.js",
    "files": "",
    "link": "https://eshitabhawsar.netlify.app/",
    "imgs": "https://i.imgur.com/vdsSvGp.png"
  }
]
